selenium_youtube_chrome/__init__.py
selenium_youtube_chrome/youtube.py
selenium_youtube_chrome-0.0.5.dist-info/LICENSE
selenium_youtube_chrome-0.0.5.dist-info/METADATA
selenium_youtube_chrome-0.0.5.dist-info/WHEEL
selenium_youtube_chrome-0.0.5.dist-info/top_level.txt
selenium_youtube_chrome-0.0.5.dist-info/RECORD
